py_vectorbase_utils/VectorBaseUtils.py
py_vectorbase_utils/__init__.py
py_vectorbase_utils/download_genome.py
py_vectorbase_utils-0.2.2.dist-info/LICENSE
py_vectorbase_utils-0.2.2.dist-info/METADATA
py_vectorbase_utils-0.2.2.dist-info/WHEEL
py_vectorbase_utils-0.2.2.dist-info/top_level.txt
py_vectorbase_utils-0.2.2.dist-info/RECORD
