Metadata-Version: 2.1
Name: py-vectorbase-utils
Version: 0.2.2
Summary: Collection of utilities to use VectorBase with python.
Home-page: https://gitlab.com/RomainFeron/py_vectorbase_utils
Author: Romain Feron
Author-email: romain.feron.91@gmail.com
License: GPLv3
Platform: UNKNOWN
Classifier: License :: OSI Approved :: GNU General Public License v3 or later (GPLv3+)
Classifier: Programming Language :: Python
Classifier: Programming Language :: Python :: 3
Classifier: Programming Language :: Python :: 3.6
Requires-Python: >=3.6.0
Requires-Dist: requests
Requires-Dist: py-vectorbase-rest
Requires-Dist: Biopython
